Metadata-Version: 2.1
Name: odoo14-addon-l10n-it-fiscalcode-sale
Version: 14.0.1.0.1.dev3
Summary: Mostra il codice fiscale del cliente nella stampa del preventivo
Home-page: https://github.com/OCA/l10n-italy/tree/12.0/l10n_it_fiscalcode_sale
Author: TAKOBI, Nextev Srl, Odoo Community Association (OCA)
Author-email: support@odoo-community.org
License: AGPL-3
Platform: UNKNOWN
Classifier: Programming Language :: Python
Classifier: Framework :: Odoo
Classifier: Framework :: Odoo :: 14.0
Classifier: License :: OSI Approved :: GNU Affero General Public License v3
Classifier: Development Status :: 4 - Beta
Requires-Python: >=3.6
Requires-Dist: odoo14-addon-l10n-it-fiscalcode
Requires-Dist: odoo <14.1dev,>=14.0a
